LICENSE
MANIFEST.in
README.rst
setup.cfg
setup.py
sentry_auth_gitlab/__init__.py
sentry_auth_gitlab/client.py
sentry_auth_gitlab/constants.py
sentry_auth_gitlab/provider.py
sentry_auth_gitlab/views.py
sentry_auth_gitlab.egg-info/PKG-INFO
sentry_auth_gitlab.egg-info/SOURCES.txt
sentry_auth_gitlab.egg-info/dependency_links.txt
sentry_auth_gitlab.egg-info/entry_points.txt
sentry_auth_gitlab.egg-info/not-zip-safe
sentry_auth_gitlab.egg-info/requires.txt
sentry_auth_gitlab.egg-info/top_level.txt