Metadata-Version: 1.1
Name: sentry-auth-gitlab
Version: 0.0.2
Summary: Gitlab authentication provider for Sentry
Home-page: https://github.com/skylothar
Author: Sky Lothar
Author-email: allothar@gmail.com@gmail.com
License: UNKNOWN
Platform: UNKNOWN
Classifier: Intended Audience :: Developers
Classifier: Intended Audience :: System Administrators
Classifier: Operating System :: OS Independent
Classifier: Topic :: Software Development
